CHANGES.rst
MANIFEST.in
README.rst
setup.py
transmogrify/__init__.py
transmogrify.print.egg-info/PKG-INFO
transmogrify.print.egg-info/SOURCES.txt
transmogrify.print.egg-info/dependency_links.txt
transmogrify.print.egg-info/entry_points.txt
transmogrify.print.egg-info/namespace_packages.txt
transmogrify.print.egg-info/not-zip-safe
transmogrify.print.egg-info/requires.txt
transmogrify.print.egg-info/top_level.txt
transmogrify/print/__init__.py
transmogrify/print/configure.zcml
transmogrify/print/tests.py