Metadata-Version: 1.1
Name: transmogrify.print
Version: 0.6.0
Summary: Transmogrifier blueprint to print pipeline item keys
Home-page: https://github.com/collective/transmogrify.print
Author: Alex Clark
Author-email: aclark@aclark.net
License: GPL
Keywords: Plone Python Transmogrifier
Platform: UNKNOWN
Classifier: Framework :: Plone
Classifier: Programming Language :: Python :: 2.7
